textsense/__init__.py
textsense/services.py
textsense-0.1.dist-info/METADATA
textsense-0.1.dist-info/WHEEL
textsense-0.1.dist-info/top_level.txt
textsense-0.1.dist-info/RECORD
